Workbook

Sheet Instructions
A1: ⚖️ Business Play — Balance Sheet Template
A4: PURPOSE | B4: This template calculates your Financial Readiness Score (FRS) for the
B5: Golden Equilibrium framework — the foundation of your Business Play.
A7: HOW TO USE | B7: 1. Go to the 'Balance Sheet' tab
B8: 2. Enter your figures in the BLUE cells (most recent period)
B9: 3. Go to 'FRS Score' tab to see your Financial Readiness Score (0-100)
B10: 4. Upload this file to Business Play for automatic scoring
A12: COLOR CODE | B12: 🔵 Blue text = Enter your numbers here (hardcoded inputs)
B13: ⚫ Black text = Auto-calculated formulas (do not edit)
B14: 🟢 Green text = Values linked from another sheet
A16: CURRENCY | B16: Enter all amounts in your local currency (THB, USD, etc.)
B17: Be consistent — use the same currency throughout
A19: CONTACT | B19: Questions? Contact Power Ladder:
B20: 📧 dithanon@powerladder.tech
B21: 🌐 https://www.powerladder.net

Sheet Balance Sheet
A1: ⚖️ Balance Sheet | Business Play by Power Ladder
B2: Enter your figures in BLUE cells • Auto-calculations in BLACK
B3: Item | C3: Amount (Local Currency)
B5: CURRENT ASSETS
B6: Cash & Cash Equivalents
B7: Accounts Receivable (Net)
B8: Inventory (Net)
B9: Prepaid Expenses & Other Current Assets
B10: Total Current Assets | C10: =SUM(C6:C9)
B12: NON-CURRENT ASSETS
B13: Property, Plant & Equipment (Net)
B14: Intangible Assets & Goodwill
B15: Other Non-Current Assets
B16: Total Non-Current Assets | C16: =SUM(C13:C15)
B18: TOTAL ASSETS | C18: =C10+C16
B20: CURRENT LIABILITIES
B21: Accounts Payable
B22: Short-Term Debt & Current Portion of LTD
B23: Accrued Expenses & Other Current Liabilities
B24: Total Current Liabilities | C24: =SUM(C21:C23)
B26: NON-CURRENT LIABILITIES
B27: Long-Term Debt
B28: Deferred Tax Liabilities
B29: Other Non-Current Liabilities
B30: Total Non-Current Liabilities | C30: =SUM(C27:C29)
B32: TOTAL LIABILITIES | C32: =C24+C30
B34: SHAREHOLDERS' EQUITY
B35: Paid-In Capital / Share Capital
B36: Retained Earnings
B37: Other Equity Components
B38: TOTAL EQUITY | C38: =SUM(C35:C37)
B40: CHECK: Total Assets = Total Liabilities + Equity | C40: =C18-C32-C38

Sheet FRS Score
A1: ⚖️ Financial Readiness Score (FRS) | Golden Equilibrium
B2: FRS measures your capacity to carry inventory without endangering cash flow (0 = extreme risk, 100 = very safe)
B3: Metric | C3: Value | D3: FRS Component (0-100)
B4: LIQUIDITY RATIOS (Weight: 40%)
B5: Current Ratio (Current Assets ÷ Current Liabilities) | C5: =IF('Balance Sheet'!C10<>0,'Balance Sheet'!C10/'Balance Sheet'!C24,0) | D5: =MIN(100, MAX(0, (C5-1)*33.33))
B6: Quick Ratio ((Cash + Receivables) ÷ Current Liabilities) | C6: =IF('Balance Sheet'!C24<>0,('Balance Sheet'!C6+'Balance Sheet'!C7)/'Balance Sheet'!C24,0) | D6: =MIN(100, MAX(0, C6*50))
B8: LEVERAGE RATIOS (Weight: 30%)
B9: Debt-to-Equity Ratio (Total Liabilities ÷ Total Equity) | C9: =IF('Balance Sheet'!C38<>0,'Balance Sheet'!C32/'Balance Sheet'!C38,999) | D9: =MIN(100, MAX(0, (3-C9)*25))
B10: Working Capital % of Total Assets | C10: =IF('Balance Sheet'!C18<>0,('Balance Sheet'!C10-'Balance Sheet'!C24)/'Balance Sheet'!C18,0) | D10: =MIN(100, MAX(0, C10*200))
B12: CASH POSITION (Weight: 30%)
B13: Cash % of Total Assets | C13: =IF('Balance Sheet'!C18<>0,'Balance Sheet'!C6/'Balance Sheet'!C18,0) | D13: =MIN(100, MAX(0, C13*300))
B14: Inventory % of Current Assets (lower = better liquidity) | C14: =IF('Balance Sheet'!C10<>0,'Balance Sheet'!C8/'Balance Sheet'!C10,0) | D14: =MIN(100, MAX(0, (1-C14)*100))
B16: 🐪 YOUR FINANCIAL RISK SCORE (FRS) → Upload to Business Play | D16: =ROUND(0.40*(D5+D6)/2 + 0.30*(D9+D10)/2 + 0.30*(D13+D14)/2, 1)
B18: FRS Guide: 0–40 = High Risk 🔴 | 41–70 = Moderate Risk 🟡 | 71–100 = Low Risk 🟢
